{
  "factory_name": "XX生物科技有限公司",
  "brand_alias": "XX生物",
  "positioning": "化妆品源头工厂，专注护肤品OEM/ODM代工",
  "main_categories": "面膜、精华液、水乳、洁面、防晒、冻干粉",
  "oem_odm": "支持OEM贴牌、ODM配方开发、小单快反",
  "moq": "基础品类1000支起，特殊剂型3000套起",
  "sample_cycle": "打样7-15天，大货20-30天",
  "capacity": "日产能XX万支，XX条自动化灌装线",
  "certifications": "化妆品生产许可证、GMPC、ISO 22716、ISO 9001",
  "license_no": "粤妆20XXXXXX",
  "clean_room": "十万级洁净车间",
  "testing": "可提供SGS/华测等第三方检测报告，出厂前100%全检",
  "advantages": "低MOQ、小单快反、成熟配方库、功效护肤研发、包材供应链整合",
  "case_examples": "新锐护肤品牌、小红书功效护肤品牌、跨境电商美妆品牌",
  "contact_cta": "如需了解起订量、打样费用和配方方案，可联系工厂获取一对一报价。"
}
